{"apiVersion":"rbac.authorization.k8s.io/v1","kind":"ClusterRoleBinding","metadata":{"annotations":{"meta.helm.sh/release-name":"kubedb","meta.helm.sh/release-namespace":"kubedb"},"creationTimestamp":"2025-04-25T12:18:28Z","labels":{"app.kubernetes.io/instance":"kubedb","app.kubernetes.io/managed-by":"Helm","app.kubernetes.io/name":"kubedb-ops-manager","app.kubernetes.io/version":"v0.39.1","helm.sh/chart":"kubedb-ops-manager-v0.39.0"},"managedFields":[{"apiVersion":"rbac.authorization.k8s.io/v1","fieldsType":"FieldsV1","fieldsV1":{"f:metadata":{"f:annotations":{".":{},"f:meta.helm.sh/release-name":{},"f:meta.helm.sh/release-namespace":{}},"f:labels":{".":{},"f:app.kubernetes.io/instance":{},"f:app.kubernetes.io/managed-by":{},"f:app.kubernetes.io/name":{},"f:app.kubernetes.io/version":{},"f:helm.sh/chart":{}}},"f:roleRef":{},"f:subjects":{}},"manager":"helm","operation":"Update","time":"2025-04-25T12:18:28Z"}],"name":"kubedb-kubedb-ops-manager","resourceVersion":"14421","uid":"2f5fd573-7b8a-444d-afff-7afbfae2064f"},"roleRef":{"apiGroup":"rbac.authorization.k8s.io","kind":"ClusterRole","name":"kubedb-kubedb-ops-manager"},"subjects":[{"kind":"ServiceAccount","name":"kubedb-kubedb-ops-manager","namespace":"kubedb"}]}