{"apiVersion":"v1","count":1,"eventTime":null,"firstTimestamp":"2025-04-25T12:12:06Z","involvedObject":{"apiVersion":"apps/v1","kind":"ReplicaSet","name":"kubedb-kubedb-autoscaler-5976fdbdd8","namespace":"kubedb","resourceVersion":"12362","uid":"95e695fa-3ad0-41c2-b013-952fbebf649a"},"kind":"Event","lastTimestamp":"2025-04-25T12:12:06Z","message":"Created pod: kubedb-kubedb-autoscaler-5976fdbdd8-whxgw","metadata":{"creationTimestamp":"2025-04-25T12:12:06Z","managedFields":[{"apiVersion":"v1","fieldsType":"FieldsV1","fieldsV1":{"f:count":{},"f:firstTimestamp":{},"f:involvedObject":{},"f:lastTimestamp":{},"f:message":{},"f:reason":{},"f:reportingComponent":{},"f:source":{"f:component":{}},"f:type":{}},"manager":"kube-controller-manager","operation":"Update","time":"2025-04-25T12:12:06Z"}],"name":"kubedb-kubedb-autoscaler-5976fdbdd8.18398e9afdba88fd","namespace":"kubedb","resourceVersion":"12368","uid":"8b8b6e1e-b0c7-4136-95e7-b3e5adb28ab3"},"reason":"SuccessfulCreate","reportingComponent":"replicaset-controller","reportingInstance":"","source":{"component":"replicaset-controller"},"type":"Normal"}