{"apiVersion":"v1","count":1,"eventTime":null,"firstTimestamp":"2025-04-22T05:15:00Z","involvedObject":{"apiVersion":"v1","fieldPath":"spec.containers{trigger}","kind":"Pod","name":"trigger-cluster-resources-backup-frequent-backup-29088315-skcn4","namespace":"demo","resourceVersion":"140741","uid":"bd229a9d-2fa6-49ae-8554-2c5d1b9149ab"},"kind":"Event","lastTimestamp":"2025-04-22T05:15:00Z","message":"Started container trigger","metadata":{"creationTimestamp":"2025-04-22T05:15:00Z","managedFields":[{"apiVersion":"v1","fieldsType":"FieldsV1","fieldsV1":{"f:count":{},"f:firstTimestamp":{},"f:involvedObject":{},"f:lastTimestamp":{},"f:message":{},"f:reason":{},"f:reportingComponent":{},"f:reportingInstance":{},"f:source":{"f:component":{},"f:host":{}},"f:type":{}},"manager":"kubelet","operation":"Update","time":"2025-04-22T05:15:00Z"}],"name":"trigger-cluster-resources-backup-frequent-backup-29088315-skcn4.18388c1a642f0bea","namespace":"demo","resourceVersion":"140748","uid":"6df06928-0992-4c1c-9dcf-208294133994"},"reason":"Started","reportingComponent":"kubelet","reportingInstance":"kind-control-plane","source":{"component":"kubelet","host":"kind-control-plane"},"type":"Normal"}